{
  "OnePerson": {
    "NameKit": "One-Person",
    "product1": "Paracetamol x 1u",
    "product2": "Ibuprofen x 1u",
    "product3": "Bandages Medical x 1u",
    "product4": "Isopropyl Alcohol 70% x 1u",
    "product5": "Diclofenac Gel 1% x 1u",
    "product6": "KN95 Face Masks x 1u",
    "product7": "Adhesive Tape Medical x 1u",
    "product8": "Canned tuna in oil x 1u",
    "product9": "Cookies x 1u",
    "product10": "Chocolates x 1u",
    "product11": "Legumes x 1u",
    "product12": "Warm Clothing x 1u",
    "product13": "Blankets x 1u",
    "product14": "Hat and Gloves Set x 1u",
    "product15": "Water bottles x 1u",
    "product16": "Battery Operated Radio x 1u",
    "product17": "Portable Charger x 1u",
    "product18": "Lanterns x 1u",
    "product19": "Wet Toilet Wipes x 1u",
    "product20": "Toilet Paper x 1u",
    "product21": "Backpack x 1u",
    "TotalPrice": 538.75
  },
  "TwoPerson": {
    "NameKit": "One-Person",
    "product1": "Paracetamol x 1u",
    "product2": "Ibuprofen x 1u",
    "product3": "Bandages Medical x 2u",
    "product4": "Isopropyl Alcohol 70% x 1u",
    "product5": "Diclofenac Gel 1% x 1u",
    "product6": "KN95 Face Masks x 1u",
    "product7": "Adhesive Tape Medical x 2u",
    "product8": "Canned tuna in oil x 4u",
    "product9": "Cookies x 2u",
    "product10": "Chocolates x 2u",
    "product11": "Legumes x 4u",
    "product12": "Warm Clothing x 2u",
    "product13": "Blankets x 2u",
    "product14": "Hat and Gloves Set x 2u",
    "product15": "Water bottles x 2u",
    "product16": "Battery Operated Radio x 1u",
    "product17": "Portable Charger x 1u",
    "product18": "Lanterns x 1u",
    "product19": "Wet Toilet Wipes x 2u",
    "product20": "Toilet Paper x 2u",
    "product21": "Backpack x 1u",
    "TotalPrice": 936.88
  }
}
